{
  "project_info": {
    "project_number": "646430676653",
    "project_id": "push-ivi-moveis-planejados",
    "storage_bucket": "push-ivi-moveis-planejados.firebasestorage.app"
  },
  "client": [
    {
      "client_info": {
        "mobilesdk_app_id": "1:646430676653:android:e6b86d4277d5e301aa5824",
        "android_client_info": {
          "package_name": "com.ivi.marcenaria"
        }
      },
      "oauth_client": [],
      "api_key": [
        {
          "current_key": "AIzaSyDeoWboWAUWhpzZMJkofT8upUJHjwGM-_g"
        }
      ],
      "services": {
        "appinvite_service": {
          "other_platform_oauth_client": []
        }
      }
    }
  ],
  "configuration_version": "1"
}